README.md
pyproject.toml
setup.cfg
setup.py
openlineage/airflow/__init__.py
openlineage/airflow/adapter.py
openlineage/airflow/facets.py
openlineage/airflow/listener.py
openlineage/airflow/macros.py
openlineage/airflow/plugin.py
openlineage/airflow/utils.py
openlineage/airflow/version.py
openlineage/airflow/extractors/__init__.py
openlineage/airflow/extractors/athena_extractor.py
openlineage/airflow/extractors/base.py
openlineage/airflow/extractors/bash_extractor.py
openlineage/airflow/extractors/bigquery_extractor.py
openlineage/airflow/extractors/converters.py
openlineage/airflow/extractors/dbapi_utils.py
openlineage/airflow/extractors/dbt_cloud_extractor.py
openlineage/airflow/extractors/example_dag.py
openlineage/airflow/extractors/extractors.py
openlineage/airflow/extractors/ftp_extractor.py
openlineage/airflow/extractors/gcs_extractor.py
openlineage/airflow/extractors/great_expectations_extractor.py
openlineage/airflow/extractors/manager.py
openlineage/airflow/extractors/mysql_extractor.py
openlineage/airflow/extractors/postgres_extractor.py
openlineage/airflow/extractors/python_extractor.py
openlineage/airflow/extractors/redshift_data_extractor.py
openlineage/airflow/extractors/redshift_sql_extractor.py
openlineage/airflow/extractors/s3_extractor.py
openlineage/airflow/extractors/sagemaker_extractors.py
openlineage/airflow/extractors/sftp_extractor.py
openlineage/airflow/extractors/snowflake_extractor.py
openlineage/airflow/extractors/sql_check_extractors.py
openlineage/airflow/extractors/sql_execute_query.py
openlineage/airflow/extractors/sql_extractor.py
openlineage/airflow/extractors/trino_extractor.py
openlineage/lineage_backend/__init__.py
openlineage_airflow_tdl.egg-info/PKG-INFO
openlineage_airflow_tdl.egg-info/SOURCES.txt
openlineage_airflow_tdl.egg-info/dependency_links.txt
openlineage_airflow_tdl.egg-info/entry_points.txt
openlineage_airflow_tdl.egg-info/not-zip-safe
openlineage_airflow_tdl.egg-info/requires.txt
openlineage_airflow_tdl.egg-info/top_level.txt