Metadata-Version: 2.1
Name: openlineage-airflow-tdl
Version: 0.24.0
Summary: OpenLineage integration with Airflow
Home-page: UNKNOWN
Author: OpenLineage
License: UNKNOWN
Keywords: openlineage
Platform: UNKNOWN
Requires-Python: >=3.7
Provides-Extra: tests
Provides-Extra: airflow
Provides-Extra: dev
